Metadata-Version: 1.1
Name: tdigest-cffi
Version: 0.1.2
Summary: A data structure for accurate on-line accumulation of rank-based statistics.
Home-page: https://github.com/kpdemetriou/tdigest-cffi
Author: Phil Demetriou
Author-email: inbox@philonas.net
License: BSD
Platform: UNKNOWN
Classifier: Development Status :: 4 - Beta
Classifier: Intended Audience :: Developers
Classifier: Intended Audience :: Science/Research
Classifier: Intended Audience :: System Administrators
Classifier: Intended Audience :: Telecommunications Industry
Classifier: License :: OSI Approved :: BSD License
Classifier: Programming Language :: C
Classifier: Programming Language :: Python :: 3
Classifier: Programming Language :: Python :: 3 :: Only
Classifier: Topic :: Scientific/Engineering
Classifier: Topic :: Scientific/Engineering :: Information Analysis
Classifier: Topic :: Scientific/Engineering :: Mathematics
Classifier: Topic :: Utilities
